hyuga/__init__.py
hyuga/__main__.py
hyuga/api.hy
hyuga/cursor.hy
hyuga/global.hy
hyuga/log.hy
hyuga/lspspec.hy
hyuga/server.hy
hyuga/sym/__init__.py
hyuga/sym/doc.hy
hyuga/sym/dummy.hy
hyuga/sym/filter.hy
hyuga/sym/helper.hy
hyuga/sym/loader.hy
hyuga/sym/summary.hy
hyuga/uri/__init__.py
hyuga/uri/helper.hy
hyuga/version.hy
hyuga-1.0.0.dist-info/LICENSE
hyuga-1.0.0.dist-info/LICENSE.original
hyuga-1.0.0.dist-info/METADATA
hyuga-1.0.0.dist-info/WHEEL
hyuga-1.0.0.dist-info/entry_points.txt
hyuga-1.0.0.dist-info/RECORD
