Metadata-Version: 2.1
Name: hyuga
Version: 1.0.0
Summary: Hyuga - Yet Another Hy Language Server
License: MIT
Author: Yuuta Sakurai
Author-email: sakurai.yuta@gmail.com
Requires-Python: >=3.8,<3.13
Classifier: License :: OSI Approved :: MIT License
Classifier: Programming Language :: Python :: 3
Classifier: Programming Language :: Python :: 3.8
Classifier: Programming Language :: Python :: 3.9
Classifier: Programming Language :: Python :: 3.10
Classifier: Programming Language :: Python :: 3.11
Classifier: Programming Language :: Python :: 3.12
Requires-Dist: hy (>=1.0.0,<2.0.0)
Requires-Dist: hyrule (>=0.7,<0.8)
Requires-Dist: pygls (>=1.2.1,<2.0.0)
Requires-Dist: setuptools (>=75.2.0,<76.0.0)
Requires-Dist: toolz (>=0.12.0,<0.13.0)
